{
  "regionId": "104",
  "jsonValue": [
    {
      "inc": "614",
      "status": "",
      "star": "13",
      "town": "104",
      "name": "AL AIN ROTANA HOTEL",
      "lname": "AL AIN ROTANA HOTEL",
      "malestop": "0",
      "stamp": "0x0000000010b3055c",
      "starCount": "5*",
      "sprice": null,
      "dataa": [],
      "price": {}
    },
    {
      "inc": "715",
      "status": "",
      "star": "13",
      "town": "104",
      "name": "HILI RAYHAAN BY ROTANA",
      "lname": "HILI RAYHAAN BY ROTANA",
      "malestop": "0",
      "stamp": "0x0000000010b3060f",
      "starCount": "5*",
      "sprice": null,
      "dataa": [],
      "price": {}
    },
    {
      "inc": "815",
      "status": "",
      "star": "12",
      "town": "104",
      "name": "CITY SEASONS HOTEL, AL AIN",
      "lname": "CITY SEASONS HOTEL, AL AIN",
      "malestop": "0",
      "stamp": "0x0000000010b306c2",
      "starCount": "4*",
      "sprice": null,
      "dataa": [],
      "price": {}
    },
    {
      "inc": "942",
      "status": "",
      "star": "12",
      "town": "104",
      "name": "AYLA BAWADI HOTEL",
      "lname": "AYLA BAWADI HOTEL",
      "malestop": "0",
      "stamp": "0x0000000010b30795",
      "starCount": "4*",
      "sprice": null,
      "dataa": [],
      "price": {}
    },
    {
      "inc": "944",
      "status": "",
      "star": "12",
      "town": "104",
      "name": "AYLA HOTEL",
      "lname": "AYLA HOTEL",
      "malestop": "0",
      "stamp": "0x0000000010b30797",
      "starCount": "4*",
      "sprice": null,
      "dataa": [],
      "price": {}
    },
    {
      "inc": "959",
      "status": "",
      "star": "13",
      "town": "104",
      "name": "AYLA GRAND HOTEL ",
      "lname": "AYLA GRAND HOTEL",
      "malestop": "0",
      "stamp": "0x0000000010b3079f",
      "starCount": "5*",
      "sprice": null,
      "dataa": [],
      "price": {}
    },
    {
      "inc": "1044",
      "status": "",
      "star": "12",
      "town": "104",
      "name": "MERCURE GRAND HOTEL JEBEL HAFEET",
      "lname": "MERCURE GRAND HOTEL JEBEL HAFEET",
      "malestop": "0",
      "stamp": "0x0000000010b30958",
      "starCount": "4*",
      "sprice": null,
      "dataa": [],
      "price": {}
    },
    {
      "inc": "1374",
      "status": "",
      "star": "13",
      "town": "104",
      "name": "DANAT AL AIN RESORT",
      "lname": "DANAT AL AIN RESORT",
      "malestop": "0",
      "stamp": "0x000000007835284e",
      "starCount": "5*",
      "sprice": null,
      "dataa": [],
      "price": [
        {
          "inc": "436502506",
          "status": " ",
          "hotel": "1374",
          "room": "12",
          "htplace": "2959",
          "meal": "3",
          "datebeg": "2022-07-09T00:00:00",
          "dateend": "2022-07-12T00:00:00",
          "rqdatebeg": "2022-07-20T00:00:00",
          "rqdateend": "2022-10-31T00:00:00",
          "nights": "1",
          "spos": "-2147483647",
          "spotype": "1",
          "rroom": "-2147483647",
          "rhtplace": "-2147483647",
          "rmeal": "-2147483647",
          "price": "264.0000",
          "currency": "5",
          "nightsfrom": "1",
          "nightstill": "366",
          "useascheckin": "0",
          "stamp": "0x000000007838dd7e",
          "name": "Executive Suite",
          "lname": "Executive Suite",
          "dataa": {
            "name": "",
            "lname": ""
          },
          "sprice": null
        },
        {
          "inc": "436502571",
          "status": " ",
          "hotel": "1374",
          "room": "1409",
          "htplace": "1799",
          "meal": "7",
          "datebeg": "2022-05-16T00:00:00",
          "dateend": "2022-07-08T00:00:00",
          "rqdatebeg": "2022-07-20T00:00:00",
          "rqdateend": "2022-10-31T00:00:00",
          "nights": "1",
          "spos": "-2147483647",
          "spotype": "1",
          "rroom": "-2147483647",
          "rhtplace": "-2147483647",
          "rmeal": "-2147483647",
          "price": "185.0000",
          "currency": "5",
          "nightsfrom": "1",
          "nightstill": "366",
          "useascheckin": "0",
          "stamp": "0x000000007838ddbf",
          "name": "",
          "lname": "",
          "dataa": {
            "name": "",
            "lname": ""
          },
          "sprice": null
        },
        {
          "inc": "436502755",
          "status": " ",
          "hotel": "1374",
          "room": "3692",
          "htplace": "1799",
          "meal": "7",
          "datebeg": "2022-04-01T00:00:00",
          "dateend": "2022-04-30T00:00:00",
          "rqdatebeg": "2022-07-20T00:00:00",
          "rqdateend": "2022-10-31T00:00:00",
          "nights": "1",
          "spos": "-2147483647",
          "spotype": "1",
          "rroom": "-2147483647",
          "rhtplace": "-2147483647",
          "rmeal": "-2147483647",
          "price": "90.0000",
          "currency": "5",
          "nightsfrom": "1",
          "nightstill": "366",
          "useascheckin": "0",
          "stamp": "0x000000007838de78",
          "name": "",
          "lname": "",
          "dataa": {
            "name": "",
            "lname": ""
          },
          "sprice": null
        },
        {
          "inc": "436502795",
          "status": " ",
          "hotel": "1374",
          "room": "3693",
          "htplace": "1799",
          "meal": "7",
          "datebeg": "2022-04-01T00:00:00",
          "dateend": "2022-04-30T00:00:00",
          "rqdatebeg": "2022-07-20T00:00:00",
          "rqdateend": "2022-10-31T00:00:00",
          "nights": "1",
          "spos": "-2147483647",
          "spotype": "1",
          "rroom": "-2147483647",
          "rhtplace": "-2147483647",
          "rmeal": "-2147483647",
          "price": "104.0000",
          "currency": "5",
          "nightsfrom": "1",
          "nightstill": "366",
          "useascheckin": "0",
          "stamp": "0x000000007838dea0",
          "name": "",
          "lname": "",
          "dataa": {
            "name": "",
            "lname": ""
          },
          "sprice": null
        }
      ]
    }
  ]
}
